RefractionShift/__init__.py
RefractionShift/refraction_shift.py
RefractionShift-0.1.1.dist-info/LICENSE
RefractionShift-0.1.1.dist-info/METADATA
RefractionShift-0.1.1.dist-info/WHEEL
RefractionShift-0.1.1.dist-info/top_level.txt
RefractionShift-0.1.1.dist-info/RECORD
