Metadata-Version: 2.1
Name: RefractionShift
Version: 0.1.1
Summary: A python module for computing the lateral shift due to atmospheric refraction 
Home-page: https://github.com/OneraHub/RefractionShift
Author: Hanae Labriji
Author-email: hanae.labriji@gmail.com
License: UNKNOWN
Project-URL: Bug Tracker, https://github.com/OneraHub/RefractionShift/issues
Platform: UNKNOWN
Classifier: Programming Language :: Python :: 3
Classifier: License :: OSI Approved :: GNU General Public License (GPL)
Classifier: Operating System :: OS Independent
Requires-Python: >=3.6
License-File: LICENSE
